opyncorporates/__init__.py
opyncorporates/api.py
opyncorporates/engines.py
opyncorporates-0.1.0.dist-info/LICENSE
opyncorporates-0.1.0.dist-info/METADATA
opyncorporates-0.1.0.dist-info/WHEEL
opyncorporates-0.1.0.dist-info/top_level.txt
opyncorporates-0.1.0.dist-info/RECORD
