Metadata-Version: 2.1
Name: opyncorporates
Version: 0.1.0
Summary: a Python package for calling the OpenCorporates API
Home-page: https://opyncorporates.readthedocs.io/en/latest/
Author: Patrick J. Ryan
Author-email: pjryan126@gmail.com
License: MIT
Platform: UNKNOWN
Requires-Dist: requests
